{"name":"SquadSquared","list":[{"appid":"360940","recommended":true,"info":false,"rawDate":" December 14, 2015","epoch":1450072800000},{"appid":"394510","recommended":true,"info":false,"rawDate":" December 6, 2015","epoch":1449381600000},{"appid":"401810","recommended":true,"info":false,"rawDate":" November 22, 2015","epoch":1448172000000},{"appid":"252950","recommended":true,"info":false,"rawDate":" November 8, 2015","epoch":1446962400000},{"appid":"250900","recommended":true,"info":false,"rawDate":" November 1, 2015","epoch":1446354000000},{"appid":"270450","recommended":true,"info":false,"rawDate":" October 24, 2015","epoch":1445662800000},{"appid":"265000","recommended":true,"info":false,"rawDate":" October 19, 2015","epoch":1445230800000},{"appid":"274190","recommended":true,"info":false,"rawDate":" October 19, 2015","epoch":1445230800000},{"appid":"204300","recommended":true,"info":false,"rawDate":" October 19, 2015","epoch":1445230800000},{"appid":"355860","recommended":true,"info":false,"rawDate":" October 19, 2015","epoch":1445230800000},{"appid":"360740","recommended":true,"info":false,"rawDate":" October 19, 2015","epoch":1445230800000},{"appid":"274350","recommended":true,"info":false,"rawDate":" October 18, 2015","epoch":1445144400000},{"appid":"375820","recommended":true,"info":false,"rawDate":" October 18, 2015","epoch":1445144400000},{"appid":"280180","recommended":true,"info":false,"rawDate":" October 18, 2015","epoch":1445144400000},{"appid":"337320","recommended":true,"info":false,"rawDate":" October 18, 2015","epoch":1445144400000},{"appid":"341800","recommended":true,"info":false,"rawDate":" October 18, 2015","epoch":1445144400000}]}