{"name":"Critz &amp; Giggles","list":[{"appid":"394510","recommended":true,"info":false},{"appid":"377160","recommended":true,"info":false},{"appid":"301640","recommended":true,"info":false},{"appid":"22600","recommended":true,"info":false},{"appid":"258970","recommended":true,"info":false},{"appid":"8870","recommended":true,"info":false},{"appid":"239820","recommended":true,"info":false},{"appid":"295790","recommended":true,"info":false},{"appid":"252950","recommended":true,"info":false},{"appid":"351510","recommended":true,"info":false},{"appid":"291550","recommended":true,"info":false},{"appid":"312530","recommended":true,"info":false},{"appid":"271590","recommended":true,"info":false},{"appid":"296470","recommended":true,"info":false},{"appid":"261180","recommended":true,"info":false},{"appid":"282800","recommended":true,"info":false},{"appid":"49540","recommended":true,"info":false},{"appid":"236390","recommended":true,"info":false},{"appid":"265630","recommended":true,"info":false},{"appid":"238460","recommended":true,"info":false},{"appid":"104900","recommended":true,"info":false},{"appid":"113020","recommended":true,"info":false},{"appid":"235460","recommended":true,"info":false},{"appid":"249680","recommended":true,"info":false},{"appid":"550","recommended":true,"info":false},{"appid":"233270","recommended":true,"info":false},{"appid":"94400","recommended":true,"info":false},{"appid":"55150","recommended":true,"info":false},{"appid":"207610","recommended":true,"info":false},{"appid":"109600","recommended":true,"info":false},{"appid":"218230","recommended":true,"info":false},{"appid":"221910","recommended":true,"info":false},{"appid":"209000","recommended":true,"info":false},{"appid":"235600","recommended":true,"info":false},{"appid":"218620","recommended":true,"info":false},{"appid":"219640","recommended":true,"info":false},{"appid":"230410","recommended":true,"info":false},{"appid":"207140","recommended":true,"info":false},{"appid":"244730","recommended":true,"info":false},{"appid":"570","recommended":true,"info":false},{"appid":"730","recommended":true,"info":false},{"appid":"13230","recommended":true,"info":false},{"appid":"221040","recommended":true,"info":false},{"appid":"41070","recommended":true,"info":false},{"appid":"620","recommended":true,"info":false},{"appid":"6020","recommended":true,"info":false},{"appid":"204360","recommended":true,"info":false},{"appid":"440","recommended":true,"info":false}]}