{"name":"COMMEND ME ✔️","list":[{"appid":"730","recommended":true,"info":false},{"appid":"363490","recommended":true,"info":false},{"appid":"303390","recommended":true,"info":false},{"appid":"348020","recommended":false,"info":false},{"appid":"91200","recommended":true,"info":false},{"appid":"410210","recommended":false,"info":false},{"appid":"438020","recommended":true,"info":false},{"appid":"63380","recommended":true,"info":false},{"appid":"440","recommended":true,"info":false},{"appid":"570","recommended":true,"info":false},{"appid":"275470","recommended":true,"info":false}]}