{"name":"Traders Guild","list":[{"appid":"397060","recommended":false,"info":true,"rawDate":" December 11, 2016","epoch":1481436000000},{"appid":"403640","recommended":false,"info":false,"rawDate":" November 13, 2016","epoch":1479016800000},{"appid":"360430","recommended":true,"info":false,"rawDate":" October 26, 2016","epoch":1477458000000},{"appid":"337000","recommended":true,"info":false,"rawDate":" September 7, 2016","epoch":1473224400000},{"appid":"420070","recommended":true,"info":false,"rawDate":" August 3, 2016","epoch":1470200400000},{"appid":"498240","recommended":false,"info":false,"rawDate":" August 3, 2016","epoch":1470200400000},{"appid":"67370","recommended":true,"info":false,"rawDate":" July 4, 2016","epoch":1467608400000},{"appid":"271590","recommended":true,"info":false,"rawDate":" June 11, 2015","epoch":1433998800000},{"appid":"22380","recommended":true,"info":false,"rawDate":" April 19, 2015","epoch":1429419600000},{"appid":"4570","recommended":true,"info":false,"rawDate":" April 19, 2015","epoch":1429419600000},{"appid":"250520","recommended":true,"info":false,"rawDate":" April 19, 2015","epoch":1429419600000},{"appid":"259680","recommended":true,"info":false,"rawDate":" April 19, 2015","epoch":1429419600000},{"appid":"219740","recommended":true,"info":false,"rawDate":" April 19, 2015","epoch":1429419600000},{"appid":"332500","recommended":true,"info":false,"rawDate":" April 19, 2015","epoch":1429419600000},{"appid":"233470","recommended":true,"info":false,"rawDate":" April 19, 2015","epoch":1429419600000},{"appid":"273350","recommended":true,"info":false,"rawDate":" April 19, 2015","epoch":1429419600000},{"appid":"288040","recommended":true,"info":false,"rawDate":" April 19, 2015","epoch":1429419600000},{"appid":"304930","recommended":true,"info":false,"rawDate":" April 19, 2015","epoch":1429419600000},{"appid":"213670","recommended":true,"info":false,"rawDate":" April 19, 2015","epoch":1429419600000},{"appid":"325430","recommended":true,"info":false,"rawDate":" April 19, 2015","epoch":1429419600000},{"appid":"235360","recommended":true,"info":false,"rawDate":" April 19, 2015","epoch":1429419600000},{"appid":"241540","recommended":true,"info":false,"rawDate":" April 19, 2015","epoch":1429419600000},{"appid":"300380","recommended":true,"info":false,"rawDate":" April 19, 2015","epoch":1429419600000},{"appid":"241930","recommended":true,"info":false,"rawDate":" April 19, 2015","epoch":1429419600000},{"appid":"261640","recommended":true,"info":false,"rawDate":" April 19, 2015","epoch":1429419600000},{"appid":"33680","recommended":true,"info":false,"rawDate":" April 19, 2015","epoch":1429419600000},{"appid":"8500","recommended":true,"info":false,"rawDate":" April 19, 2015","epoch":1429419600000}]}