{"name":"Official MrWoodenSheep Group","list":[{"appid":"341800","recommended":true,"info":false},{"appid":"290340","recommended":true,"info":false},{"appid":"480430","recommended":true,"info":false},{"appid":"384490","recommended":true,"info":false},{"appid":"304430","recommended":true,"info":false},{"appid":"391540","recommended":true,"info":false},{"appid":"359550","recommended":true,"info":false},{"appid":"285900","recommended":true,"info":false},{"appid":"237630","recommended":true,"info":false},{"appid":"323320","recommended":true,"info":false},{"appid":"383870","recommended":true,"info":false},{"appid":"391220","recommended":true,"info":false},{"appid":"302510","recommended":true,"info":false},{"appid":"405640","recommended":true,"info":false},{"appid":"427730","recommended":true,"info":false},{"appid":"401810","recommended":true,"info":false},{"appid":"360940","recommended":true,"info":false},{"appid":"337480","recommended":true,"info":false},{"appid":"234140","recommended":true,"info":false},{"appid":"235540","recommended":true,"info":false},{"appid":"403190","recommended":true,"info":false},{"appid":"243160","recommended":true,"info":false},{"appid":"375820","recommended":true,"info":false},{"appid":"396310","recommended":true,"info":false},{"appid":"282140","recommended":true,"info":false},{"appid":"293780","recommended":true,"info":false},{"appid":"355860","recommended":true,"info":false},{"appid":"220440","recommended":true,"info":false},{"appid":"252110","recommended":true,"info":false},{"appid":"274350","recommended":true,"info":false},{"appid":"334120","recommended":true,"info":false},{"appid":"357300","recommended":true,"info":false},{"appid":"367450","recommended":true,"info":false},{"appid":"381120","recommended":true,"info":false},{"appid":"308560","recommended":true,"info":false},{"appid":"347510","recommended":true,"info":false},{"appid":"365660","recommended":true,"info":false},{"appid":"378660","recommended":true,"info":false},{"appid":"368310","recommended":true,"info":false},{"appid":"384280","recommended":true,"info":false},{"appid":"356250","recommended":true,"info":false},{"appid":"278420","recommended":true,"info":false},{"appid":"385710","recommended":true,"info":false},{"appid":"383120","recommended":true,"info":false},{"appid":"301860","recommended":true,"info":false},{"appid":"327060","recommended":true,"info":false},{"appid":"252950","recommended":true,"info":false},{"appid":"338040","recommended":true,"info":false},{"appid":"350740","recommended":true,"info":false},{"appid":"361550","recommended":true,"info":false},{"appid":"352070","recommended":true,"info":false},{"appid":"375250","recommended":true,"info":false},{"appid":"274270","recommended":true,"info":false},{"appid":"263040","recommended":true,"info":false},{"appid":"274920","recommended":true,"info":false},{"appid":"286160","recommended":true,"info":false},{"appid":"250620","recommended":true,"info":false},{"appid":"275100","recommended":true,"info":false},{"appid":"22000","recommended":true,"info":false},{"appid":"236090","recommended":true,"info":false},{"appid":"22600","recommended":true,"info":false},{"appid":"70600","recommended":true,"info":false},{"appid":"200170","recommended":true,"info":false},{"appid":"238460","recommended":true,"info":false},{"appid":"247020","recommended":true,"info":false},{"appid":"244710","recommended":true,"info":false},{"appid":"287390","recommended":true,"info":false},{"appid":"242550","recommended":true,"info":false},{"appid":"207490","recommended":true,"info":false},{"appid":"215690","recommended":true,"info":false},{"appid":"245280","recommended":true,"info":false}]}