{"name":"Super Adventures in Gaming","list":[{"appid":"7670","recommended":true,"info":false},{"appid":"413150","recommended":true,"info":false},{"appid":"31170","recommended":true,"info":false},{"appid":"240760","recommended":true,"info":false},{"appid":"203160","recommended":true,"info":false},{"appid":"72850","recommended":true,"info":false},{"appid":"250760","recommended":true,"info":false},{"appid":"278080","recommended":true,"info":false},{"appid":"2100","recommended":true,"info":false},{"appid":"4720","recommended":true,"info":false},{"appid":"201810","recommended":true,"info":false},{"appid":"21690","recommended":true,"info":false},{"appid":"17460","recommended":true,"info":false},{"appid":"13520","recommended":true,"info":false},{"appid":"307690","recommended":true,"info":false},{"appid":"206420","recommended":true,"info":false},{"appid":"9480","recommended":true,"info":false},{"appid":"242530","recommended":true,"info":false},{"appid":"206190","recommended":true,"info":false},{"appid":"21090","recommended":true,"info":false},{"appid":"2310","recommended":true,"info":false},{"appid":"263560","recommended":true,"info":false},{"appid":"57900","recommended":true,"info":false},{"appid":"17450","recommended":true,"info":false},{"appid":"219150","recommended":true,"info":false},{"appid":"211260","recommended":true,"info":false},{"appid":"15130","recommended":true,"info":false},{"appid":"55230","recommended":true,"info":false},{"appid":"3830","recommended":true,"info":false},{"appid":"32400","recommended":true,"info":false},{"appid":"221260","recommended":true,"info":false},{"appid":"241600","recommended":true,"info":false},{"appid":"224820","recommended":true,"info":false},{"appid":"267980","recommended":true,"info":false},{"appid":"9050","recommended":true,"info":false},{"appid":"22380","recommended":true,"info":false},{"appid":"9200","recommended":true,"info":false},{"appid":"22370","recommended":true,"info":false},{"appid":"12140","recommended":true,"info":false},{"appid":"2630","recommended":true,"info":false},{"appid":"2390","recommended":true,"info":false},{"appid":"252630","recommended":true,"info":false},{"appid":"224760","recommended":true,"info":false},{"appid":"12150","recommended":true,"info":false},{"appid":"32380","recommended":true,"info":false},{"appid":"32370","recommended":true,"info":false},{"appid":"224920","recommended":true,"info":false},{"appid":"204100","recommended":true,"info":false},{"appid":"47790","recommended":true,"info":false},{"appid":"7010","recommended":true,"info":false}]}