{"name":"Gaming Hidden Gems","list":[{"appid":"307580","recommended":true,"info":false,"rawDate":" April 25","epoch":1493096400000},{"appid":"252110","recommended":true,"info":false,"rawDate":" April 23","epoch":1492923600000},{"appid":"15270","recommended":true,"info":false,"rawDate":" April 22","epoch":1492837200000},{"appid":"373390","recommended":true,"info":false,"rawDate":" April 21","epoch":1492750800000},{"appid":"397740","recommended":true,"info":false,"rawDate":" April 20","epoch":1492664400000},{"appid":"22180","recommended":true,"info":false,"rawDate":" April 19","epoch":1492578000000},{"appid":"394390","recommended":true,"info":false,"rawDate":" April 3","epoch":1491195600000},{"appid":"50620","recommended":true,"info":false,"rawDate":" March 24","epoch":1490331600000},{"appid":"1930","recommended":true,"info":false,"rawDate":" January 14","epoch":1484373600000},{"appid":"270630","recommended":true,"info":false,"rawDate":" December 29, 2016","epoch":1482991200000},{"appid":"50000","recommended":true,"info":false,"rawDate":" November 26, 2016","epoch":1480140000000},{"appid":"252150","recommended":true,"info":false,"rawDate":" April 8, 2016","epoch":1460091600000},{"appid":"354650","recommended":true,"info":false,"rawDate":" April 6, 2016","epoch":1459918800000},{"appid":"269810","recommended":true,"info":false,"rawDate":" December 27, 2015","epoch":1451196000000},{"appid":"42650","recommended":true,"info":false,"rawDate":" December 15, 2015","epoch":1450159200000},{"appid":"277460","recommended":true,"info":false,"rawDate":" November 26, 2015","epoch":1448517600000},{"appid":"333300","recommended":true,"info":false,"rawDate":" November 18, 2015","epoch":1447826400000},{"appid":"261570","recommended":true,"info":false,"rawDate":" November 14, 2015","epoch":1447480800000},{"appid":"324680","recommended":true,"info":false,"rawDate":" November 12, 2015","epoch":1447308000000},{"appid":"384110","recommended":true,"info":false,"rawDate":" November 11, 2015","epoch":1447221600000},{"appid":"335920","recommended":true,"info":false,"rawDate":" November 10, 2015","epoch":1447135200000},{"appid":"248730","recommended":true,"info":false,"rawDate":" November 6, 2015","epoch":1446789600000},{"appid":"1300","recommended":true,"info":false,"rawDate":" November 4, 2015","epoch":1446616800000},{"appid":"262790","recommended":true,"info":false,"rawDate":" November 2, 2015","epoch":1446444000000},{"appid":"324710","recommended":true,"info":false,"rawDate":" November 2, 2015","epoch":1446444000000},{"appid":"207040","recommended":true,"info":false,"rawDate":" October 30, 2015","epoch":1446181200000},{"appid":"22450","recommended":true,"info":false,"rawDate":" October 25, 2015","epoch":1445749200000},{"appid":"327520","recommended":true,"info":false,"rawDate":" October 23, 2015","epoch":1445576400000},{"appid":"15130","recommended":true,"info":false,"rawDate":" October 15, 2015","epoch":1444885200000},{"appid":"243000","recommended":true,"info":false,"rawDate":" October 3, 2015","epoch":1443848400000},{"appid":"25990","recommended":true,"info":false,"rawDate":" October 2, 2015","epoch":1443762000000},{"appid":"10130","recommended":true,"info":false,"rawDate":" September 29, 2015","epoch":1443502800000},{"appid":"221180","recommended":true,"info":false,"rawDate":" September 26, 2015","epoch":1443243600000},{"appid":"299360","recommended":true,"info":false,"rawDate":" September 25, 2015","epoch":1443157200000},{"appid":"347440","recommended":true,"info":false,"rawDate":" September 25, 2015","epoch":1443157200000},{"appid":"242940","recommended":true,"info":false,"rawDate":" September 25, 2015","epoch":1443157200000},{"appid":"243140","recommended":true,"info":false,"rawDate":" September 23, 2015","epoch":1442984400000},{"appid":"25010","recommended":true,"info":false,"rawDate":" September 23, 2015","epoch":1442984400000},{"appid":"265950","recommended":true,"info":false,"rawDate":" September 22, 2015","epoch":1442898000000},{"appid":"314230","recommended":true,"info":false,"rawDate":" September 22, 2015","epoch":1442898000000},{"appid":"264080","recommended":true,"info":false,"rawDate":" September 22, 2015","epoch":1442898000000},{"appid":"327740","recommended":true,"info":false,"rawDate":" September 22, 2015","epoch":1442898000000},{"appid":"4800","recommended":true,"info":false,"rawDate":" September 22, 2015","epoch":1442898000000},{"appid":"37260","recommended":true,"info":false,"rawDate":" September 22, 2015","epoch":1442898000000},{"appid":"16720","recommended":true,"info":false,"rawDate":" September 21, 2015","epoch":1442811600000},{"appid":"329640","recommended":true,"info":false,"rawDate":" September 21, 2015","epoch":1442811600000},{"appid":"34410","recommended":true,"info":false,"rawDate":" September 21, 2015","epoch":1442811600000},{"appid":"272600","recommended":true,"info":false,"rawDate":" September 21, 2015","epoch":1442811600000},{"appid":"275570","recommended":true,"info":false,"rawDate":" September 20, 2015","epoch":1442725200000},{"appid":"319250","recommended":true,"info":false,"rawDate":" September 20, 2015","epoch":1442725200000},{"appid":"358370","recommended":true,"info":false,"rawDate":" September 20, 2015","epoch":1442725200000},{"appid":"38440","recommended":true,"info":false,"rawDate":" September 19, 2015","epoch":1442638800000},{"appid":"249590","recommended":true,"info":false,"rawDate":" September 18, 2015","epoch":1442552400000},{"appid":"324810","recommended":true,"info":false,"rawDate":" September 18, 2015","epoch":1442552400000},{"appid":"6010","recommended":true,"info":false,"rawDate":" September 18, 2015","epoch":1442552400000},{"appid":"7020","recommended":true,"info":false,"rawDate":" September 17, 2015","epoch":1442466000000},{"appid":"269670","recommended":true,"info":false,"rawDate":" September 17, 2015","epoch":1442466000000},{"appid":"366220","recommended":true,"info":false,"rawDate":" September 17, 2015","epoch":1442466000000},{"appid":"288160","recommended":true,"info":false,"rawDate":" September 17, 2015","epoch":1442466000000},{"appid":"297290","recommended":true,"info":false,"rawDate":" September 17, 2015","epoch":1442466000000},{"appid":"224920","recommended":true,"info":false,"rawDate":" September 17, 2015","epoch":1442466000000},{"appid":"224300","recommended":true,"info":false,"rawDate":" September 17, 2015","epoch":1442466000000},{"appid":"264060","recommended":true,"info":false,"rawDate":" September 17, 2015","epoch":1442466000000},{"appid":"25830","recommended":true,"info":false,"rawDate":" September 17, 2015","epoch":1442466000000},{"appid":"1700","recommended":true,"info":false,"rawDate":" September 17, 2015","epoch":1442466000000},{"appid":"92600","recommended":true,"info":false,"rawDate":" September 17, 2015","epoch":1442466000000},{"appid":"21090","recommended":true,"info":false,"rawDate":" September 17, 2015","epoch":1442466000000},{"appid":"330390","recommended":true,"info":false,"rawDate":" September 17, 2015","epoch":1442466000000},{"appid":"10680","recommended":true,"info":false,"rawDate":" September 17, 2015","epoch":1442466000000},{"appid":"3730","recommended":true,"info":false,"rawDate":" September 17, 2015","epoch":1442466000000},{"appid":"19900","recommended":true,"info":false,"rawDate":" September 16, 2015","epoch":1442379600000},{"appid":"204530","recommended":true,"info":false,"rawDate":" September 16, 2015","epoch":1442379600000},{"appid":"389900","recommended":true,"info":false,"rawDate":" September 16, 2015","epoch":1442379600000},{"appid":"289620","recommended":true,"info":false,"rawDate":" September 15, 2015","epoch":1442293200000},{"appid":"229580","recommended":true,"info":false,"rawDate":" September 11, 2015","epoch":1441947600000},{"appid":"245280","recommended":true,"info":false,"rawDate":" September 11, 2015","epoch":1441947600000},{"appid":"302610","recommended":true,"info":false,"rawDate":" September 8, 2015","epoch":1441688400000},{"appid":"251770","recommended":true,"info":false,"rawDate":" September 6, 2015","epoch":1441515600000},{"appid":"392020","recommended":true,"info":false,"rawDate":" September 6, 2015","epoch":1441515600000},{"appid":"287260","recommended":true,"info":false,"rawDate":" September 6, 2015","epoch":1441515600000},{"appid":"210950","recommended":true,"info":false,"rawDate":" September 6, 2015","epoch":1441515600000},{"appid":"336610","recommended":true,"info":false,"rawDate":" September 6, 2015","epoch":1441515600000},{"appid":"223510","recommended":true,"info":false,"rawDate":" September 6, 2015","epoch":1441515600000},{"appid":"305050","recommended":true,"info":false,"rawDate":" September 4, 2015","epoch":1441342800000},{"appid":"94300","recommended":true,"info":false,"rawDate":" September 2, 2015","epoch":1441170000000},{"appid":"37600","recommended":true,"info":false,"rawDate":" September 1, 2015","epoch":1441083600000},{"appid":"290260","recommended":true,"info":false,"rawDate":" September 1, 2015","epoch":1441083600000},{"appid":"219990","recommended":true,"info":false,"rawDate":" August 31, 2015","epoch":1440997200000},{"appid":"15750","recommended":true,"info":false,"rawDate":" August 29, 2015","epoch":1440824400000},{"appid":"356430","recommended":true,"info":false,"rawDate":" August 28, 2015","epoch":1440738000000},{"appid":"34312","recommended":true,"info":false,"rawDate":" August 25, 2015","epoch":1440478800000},{"appid":"35130","recommended":true,"info":false,"rawDate":" August 25, 2015","epoch":1440478800000},{"appid":"251430","recommended":true,"info":false,"rawDate":" August 25, 2015","epoch":1440478800000},{"appid":"12360","recommended":true,"info":false,"rawDate":" August 24, 2015","epoch":1440392400000},{"appid":"329130","recommended":true,"info":false,"rawDate":" August 23, 2015","epoch":1440306000000},{"appid":"21670","recommended":true,"info":false,"rawDate":" August 22, 2015","epoch":1440219600000},{"appid":"45730","recommended":true,"info":false,"rawDate":" August 22, 2015","epoch":1440219600000},{"appid":"252630","recommended":true,"info":false,"rawDate":" August 21, 2015","epoch":1440133200000},{"appid":"346970","recommended":true,"info":false,"rawDate":" August 18, 2015","epoch":1439874000000},{"appid":"38430","recommended":true,"info":false,"rawDate":" August 13, 2015","epoch":1439442000000},{"appid":"37000","recommended":true,"info":false,"rawDate":" August 11, 2015","epoch":1439269200000},{"appid":"293240","recommended":true,"info":false,"rawDate":" August 11, 2015","epoch":1439269200000},{"appid":"322550","recommended":true,"info":false,"rawDate":" August 10, 2015","epoch":1439182800000},{"appid":"243120","recommended":true,"info":false,"rawDate":" August 6, 2015","epoch":1438837200000},{"appid":"252550","recommended":true,"info":false,"rawDate":" August 6, 2015","epoch":1438837200000},{"appid":"327930","recommended":true,"info":false,"rawDate":" August 4, 2015","epoch":1438664400000},{"appid":"214790","recommended":true,"info":false,"rawDate":" August 3, 2015","epoch":1438578000000},{"appid":"265690","recommended":true,"info":false,"rawDate":" August 1, 2015","epoch":1438405200000},{"appid":"98800","recommended":true,"info":false,"rawDate":" July 28, 2015","epoch":1438059600000},{"appid":"293660","recommended":true,"info":false,"rawDate":" July 27, 2015","epoch":1437973200000},{"appid":"312720","recommended":true,"info":false,"rawDate":" July 27, 2015","epoch":1437973200000},{"appid":"257510","recommended":true,"info":false,"rawDate":" July 25, 2015","epoch":1437800400000},{"appid":"311800","recommended":true,"info":false,"rawDate":" July 22, 2015","epoch":1437541200000},{"appid":"280220","recommended":true,"info":false,"rawDate":" July 21, 2015","epoch":1437454800000},{"appid":"205910","recommended":true,"info":false,"rawDate":" July 21, 2015","epoch":1437454800000},{"appid":"314590","recommended":true,"info":false,"rawDate":" July 18, 2015","epoch":1437195600000},{"appid":"243040","recommended":true,"info":false,"rawDate":" July 14, 2015","epoch":1436850000000},{"appid":"3800","recommended":true,"info":false,"rawDate":" July 14, 2015","epoch":1436850000000},{"appid":"329190","recommended":true,"info":false,"rawDate":" July 13, 2015","epoch":1436763600000},{"appid":"39670","recommended":true,"info":false,"rawDate":" July 13, 2015","epoch":1436763600000},{"appid":"319560","recommended":true,"info":false,"rawDate":" July 13, 2015","epoch":1436763600000},{"appid":"38740","recommended":true,"info":false,"rawDate":" July 12, 2015","epoch":1436677200000},{"appid":"205730","recommended":true,"info":false,"rawDate":" July 12, 2015","epoch":1436677200000},{"appid":"91100","recommended":true,"info":false,"rawDate":" July 12, 2015","epoch":1436677200000},{"appid":"255390","recommended":true,"info":false,"rawDate":" July 11, 2015","epoch":1436590800000},{"appid":"333930","recommended":true,"info":false,"rawDate":" July 10, 2015","epoch":1436504400000},{"appid":"335670","recommended":true,"info":false,"rawDate":" July 9, 2015","epoch":1436418000000},{"appid":"300340","recommended":true,"info":false,"rawDate":" July 9, 2015","epoch":1436418000000},{"appid":"242820","recommended":true,"info":false,"rawDate":" July 7, 2015","epoch":1436245200000},{"appid":"244710","recommended":true,"info":false,"rawDate":" July 7, 2015","epoch":1436245200000},{"appid":"343710","recommended":true,"info":false,"rawDate":" July 6, 2015","epoch":1436158800000},{"appid":"233150","recommended":true,"info":false,"rawDate":" July 6, 2015","epoch":1436158800000},{"appid":"352700","recommended":true,"info":false,"rawDate":" July 3, 2015","epoch":1435899600000},{"appid":"300570","recommended":true,"info":false,"rawDate":" July 3, 2015","epoch":1435899600000},{"appid":"21780","recommended":true,"info":false,"rawDate":" July 3, 2015","epoch":1435899600000},{"appid":"323320","recommended":true,"info":false,"rawDate":" July 3, 2015","epoch":1435899600000},{"appid":"274520","recommended":true,"info":false,"rawDate":" July 2, 2015","epoch":1435813200000},{"appid":"264710","recommended":true,"info":false,"rawDate":" July 2, 2015","epoch":1435813200000},{"appid":"227080","recommended":true,"info":false,"rawDate":" July 2, 2015","epoch":1435813200000},{"appid":"260190","recommended":true,"info":false,"rawDate":" July 1, 2015","epoch":1435726800000},{"appid":"242640","recommended":true,"info":false,"rawDate":" July 1, 2015","epoch":1435726800000},{"appid":"204240","recommended":true,"info":false,"rawDate":" June 29, 2015","epoch":1435554000000},{"appid":"282030","recommended":true,"info":false,"rawDate":" June 29, 2015","epoch":1435554000000},{"appid":"250600","recommended":true,"info":false,"rawDate":" June 28, 2015","epoch":1435467600000},{"appid":"253030","recommended":true,"info":false,"rawDate":" June 28, 2015","epoch":1435467600000},{"appid":"239430","recommended":true,"info":false,"rawDate":" June 28, 2015","epoch":1435467600000},{"appid":"287020","recommended":true,"info":false,"rawDate":" June 28, 2015","epoch":1435467600000},{"appid":"215530","recommended":true,"info":false,"rawDate":" June 28, 2015","epoch":1435467600000},{"appid":"304930","recommended":true,"info":false,"rawDate":" June 27, 2015","epoch":1435381200000},{"appid":"228300","recommended":true,"info":false,"rawDate":" June 26, 2015","epoch":1435294800000},{"appid":"233230","recommended":true,"info":false,"rawDate":" June 25, 2015","epoch":1435208400000},{"appid":"308040","recommended":true,"info":false,"rawDate":" June 25, 2015","epoch":1435208400000},{"appid":"244930","recommended":true,"info":false,"rawDate":" June 25, 2015","epoch":1435208400000},{"appid":"368370","recommended":true,"info":false,"rawDate":" June 25, 2015","epoch":1435208400000},{"appid":"42670","recommended":true,"info":false,"rawDate":" June 23, 2015","epoch":1435035600000},{"appid":"324070","recommended":true,"info":false,"rawDate":" June 23, 2015","epoch":1435035600000},{"appid":"334070","recommended":true,"info":false,"rawDate":" June 22, 2015","epoch":1434949200000},{"appid":"220780","recommended":true,"info":false,"rawDate":" June 22, 2015","epoch":1434949200000},{"appid":"317360","recommended":true,"info":false,"rawDate":" June 22, 2015","epoch":1434949200000},{"appid":"328070","recommended":true,"info":false,"rawDate":" June 21, 2015","epoch":1434862800000},{"appid":"21980","recommended":true,"info":false,"rawDate":" June 21, 2015","epoch":1434862800000},{"appid":"265890","recommended":true,"info":false,"rawDate":" June 21, 2015","epoch":1434862800000},{"appid":"265830","recommended":true,"info":false,"rawDate":" June 21, 2015","epoch":1434862800000},{"appid":"250520","recommended":true,"info":false,"rawDate":" June 21, 2015","epoch":1434862800000},{"appid":"3720","recommended":true,"info":false,"rawDate":" June 20, 2015","epoch":1434776400000},{"appid":"224260","recommended":true,"info":false,"rawDate":" June 19, 2015","epoch":1434690000000},{"appid":"33680","recommended":true,"info":false,"rawDate":" June 19, 2015","epoch":1434690000000},{"appid":"34810","recommended":true,"info":false,"rawDate":" June 19, 2015","epoch":1434690000000},{"appid":"97100","recommended":true,"info":false,"rawDate":" June 19, 2015","epoch":1434690000000},{"appid":"94200","recommended":true,"info":false,"rawDate":" June 19, 2015","epoch":1434690000000},{"appid":"17330","recommended":true,"info":false,"rawDate":" June 19, 2015","epoch":1434690000000},{"appid":"231160","recommended":true,"info":false,"rawDate":" June 17, 2015","epoch":1434517200000},{"appid":"278360","recommended":true,"info":false,"rawDate":" June 17, 2015","epoch":1434517200000},{"appid":"3710","recommended":true,"info":false,"rawDate":" June 14, 2015","epoch":1434258000000},{"appid":"22230","recommended":true,"info":false,"rawDate":" June 13, 2015","epoch":1434171600000},{"appid":"6420","recommended":true,"info":false,"rawDate":" June 13, 2015","epoch":1434171600000},{"appid":"33210","recommended":true,"info":false,"rawDate":" June 12, 2015","epoch":1434085200000},{"appid":"215280","recommended":true,"info":false,"rawDate":" June 3, 2015","epoch":1433307600000},{"appid":"40700","recommended":true,"info":false,"rawDate":" June 1, 2015","epoch":1433134800000},{"appid":"27000","recommended":true,"info":false,"rawDate":" May 31, 2015","epoch":1433048400000},{"appid":"21600","recommended":true,"info":false,"rawDate":" May 29, 2015","epoch":1432875600000},{"appid":"29900","recommended":true,"info":false,"rawDate":" May 29, 2015","epoch":1432875600000},{"appid":"38460","recommended":true,"info":false,"rawDate":" May 29, 2015","epoch":1432875600000},{"appid":"38450","recommended":true,"info":false,"rawDate":" May 29, 2015","epoch":1432875600000},{"appid":"44340","recommended":true,"info":false,"rawDate":" May 29, 2015","epoch":1432875600000},{"appid":"34010","recommended":true,"info":false,"rawDate":" May 29, 2015","epoch":1432875600000},{"appid":"374570","recommended":true,"info":false,"rawDate":" May 29, 2015","epoch":1432875600000},{"appid":"354380","recommended":true,"info":false,"rawDate":" May 28, 2015","epoch":1432789200000},{"appid":"9480","recommended":true,"info":false,"rawDate":" May 28, 2015","epoch":1432789200000},{"appid":"249680","recommended":true,"info":false,"rawDate":" May 28, 2015","epoch":1432789200000},{"appid":"299030","recommended":true,"info":false,"rawDate":" May 28, 2015","epoch":1432789200000},{"appid":"71230","recommended":true,"info":false,"rawDate":" May 28, 2015","epoch":1432789200000},{"appid":"98400","recommended":true,"info":false,"rawDate":" May 28, 2015","epoch":1432789200000},{"appid":"227000","recommended":true,"info":false,"rawDate":" May 28, 2015","epoch":1432789200000},{"appid":"357070","recommended":true,"info":false,"rawDate":" May 28, 2015","epoch":1432789200000},{"appid":"227200","recommended":true,"info":false,"rawDate":" May 28, 2015","epoch":1432789200000},{"appid":"209270","recommended":true,"info":false,"rawDate":" May 28, 2015","epoch":1432789200000},{"appid":"250580","recommended":true,"info":false,"rawDate":" May 27, 2015","epoch":1432702800000},{"appid":"211180","recommended":true,"info":false,"rawDate":" May 27, 2015","epoch":1432702800000},{"appid":"6200","recommended":true,"info":false,"rawDate":" May 27, 2015","epoch":1432702800000},{"appid":"211400","recommended":true,"info":false,"rawDate":" May 27, 2015","epoch":1432702800000},{"appid":"242920","recommended":true,"info":false,"rawDate":" May 27, 2015","epoch":1432702800000},{"appid":"108710","recommended":true,"info":false,"rawDate":" May 25, 2015","epoch":1432530000000},{"appid":"107800","recommended":true,"info":false,"rawDate":" May 25, 2015","epoch":1432530000000},{"appid":"19680","recommended":true,"info":false,"rawDate":" May 19, 2015","epoch":1432011600000},{"appid":"239140","recommended":true,"info":false,"rawDate":" April 8, 2015","epoch":1428469200000},{"appid":"3830","recommended":true,"info":false,"rawDate":" April 8, 2015","epoch":1428469200000}]}