{"name":"Saint_Satan","list":[{"appid":"318600","recommended":true,"info":false},{"appid":"239140","recommended":true,"info":false},{"appid":"262060","recommended":true,"info":false},{"appid":"303210","recommended":true,"info":false},{"appid":"355630","recommended":true,"info":false},{"appid":"235540","recommended":true,"info":false},{"appid":"287700","recommended":true,"info":false},{"appid":"391720","recommended":true,"info":false},{"appid":"282140","recommended":true,"info":false},{"appid":"208650","recommended":true,"info":false},{"appid":"247660","recommended":true,"info":false},{"appid":"225080","recommended":true,"info":false},{"appid":"343710","recommended":true,"info":false},{"appid":"334120","recommended":true,"info":false},{"appid":"358090","recommended":true,"info":false},{"appid":"377160","recommended":true,"info":false},{"appid":"363970","recommended":true,"info":false},{"appid":"374570","recommended":true,"info":false},{"appid":"250900","recommended":true,"info":false},{"appid":"40800","recommended":true,"info":false},{"appid":"212480","recommended":true,"info":false},{"appid":"246580","recommended":true,"info":false},{"appid":"250600","recommended":true,"info":false},{"appid":"213670","recommended":true,"info":false},{"appid":"261640","recommended":true,"info":false},{"appid":"250620","recommended":true,"info":false},{"appid":"304240","recommended":true,"info":false},{"appid":"307780","recommended":true,"info":false},{"appid":"353360","recommended":true,"info":false},{"appid":"287290","recommended":true,"info":false},{"appid":"72850","recommended":true,"info":false},{"appid":"322330","recommended":true,"info":false},{"appid":"318860","recommended":true,"info":false},{"appid":"299030","recommended":true,"info":false},{"appid":"310560","recommended":true,"info":false},{"appid":"271590","recommended":true,"info":false},{"appid":"341940","recommended":true,"info":false}]}