{"name":"Survival PC Gaming","list":[{"appid":"412450","recommended":false,"info":false,"rawDate":" January 16","epoch":1484546400000},{"appid":"299740","recommended":true,"info":false,"rawDate":" January 16","epoch":1484546400000},{"appid":"242760","recommended":true,"info":false,"rawDate":" January 16","epoch":1484546400000},{"appid":"402710","recommended":true,"info":false,"rawDate":" January 16","epoch":1484546400000},{"appid":"433850","recommended":true,"info":false,"rawDate":" July 1, 2016","epoch":1467349200000},{"appid":"381210","recommended":true,"info":false,"rawDate":" July 1, 2016","epoch":1467349200000},{"appid":"360170","recommended":true,"info":false,"rawDate":" July 1, 2016","epoch":1467349200000},{"appid":"360150","recommended":true,"info":false,"rawDate":" July 3, 2015","epoch":1435899600000},{"appid":"332500","recommended":true,"info":false,"rawDate":" June 4, 2015","epoch":1433394000000},{"appid":"252490","recommended":true,"info":false,"rawDate":" June 4, 2015","epoch":1433394000000},{"appid":"322330","recommended":true,"info":false,"rawDate":" June 4, 2015","epoch":1433394000000},{"appid":"219740","recommended":true,"info":false,"rawDate":" June 4, 2015","epoch":1433394000000},{"appid":"290080","recommended":true,"info":false,"rawDate":" June 4, 2015","epoch":1433394000000},{"appid":"351290","recommended":true,"info":false,"rawDate":" June 4, 2015","epoch":1433394000000},{"appid":"264710","recommended":true,"info":false,"rawDate":" June 4, 2015","epoch":1433394000000},{"appid":"221100","recommended":true,"info":false,"rawDate":" June 4, 2015","epoch":1433394000000},{"appid":"251570","recommended":true,"info":false,"rawDate":" June 4, 2015","epoch":1433394000000},{"appid":"305620","recommended":true,"info":false,"rawDate":" June 4, 2015","epoch":1433394000000},{"appid":"295110","recommended":true,"info":false,"rawDate":" June 4, 2015","epoch":1433394000000},{"appid":"346110","recommended":true,"info":false,"rawDate":" June 4, 2015","epoch":1433394000000}]}